master/__init__.py
master/main.py
master/utils.py
master/cmd/__init__.py
master/cmd/serve.py
master/cmd/setup.py
master/k8s/__init__.py
master/k8s/k8s.py
master/server/__init__.py
master/server/join.py
master/server/server.py
tests/__init__.py
tests/install_test.py
Ocean_Agent_Master-0.0.10.dist-info/METADATA
Ocean_Agent_Master-0.0.10.dist-info/WHEEL
Ocean_Agent_Master-0.0.10.dist-info/entry_points.txt
Ocean_Agent_Master-0.0.10.dist-info/top_level.txt
Ocean_Agent_Master-0.0.10.dist-info/RECORD
